vectordeprecios/__init__.py
vectordeprecios/core/Object.py
vectordeprecios/core/__init__.py
vectordeprecios/core/Service/Service.py
vectordeprecios/core/Service/__init__.py
vectordeprecios/core/Service/Field/Field.py
vectordeprecios/core/Service/Field/FieldDataType.py
vectordeprecios/core/Service/Field/FieldQuality.py
vectordeprecios/core/Service/Field/FieldReport.py
vectordeprecios/core/Service/Field/FieldTicker.py
vectordeprecios/core/Service/Field/FieldTimeInterval.py
vectordeprecios/core/Service/Field/FieldVersion.py
vectordeprecios/core/Service/Field/__init__.py
vectordeprecios/core/Service/ServiceRequest/ServiceRequest.py
vectordeprecios/core/Service/ServiceRequest/__init__.py
vectordeprecios/core/Service/ServiceRequest/ServiceRequestDataPoint/ServiceRequestDataPoint.py
vectordeprecios/core/Service/ServiceRequest/ServiceRequestDataPoint/ServiceRequestDataPointComment.py
vectordeprecios/core/Service/ServiceRequest/ServiceRequestDataPoint/ServiceRequestDataPointReport.py
vectordeprecios/core/Service/ServiceRequest/ServiceRequestDataPoint/ServiceRequestDataPointValue.py
vectordeprecios/core/Service/ServiceRequest/ServiceRequestDataPoint/__init__.py
vectordeprecios/core/Service/ServiceRequest/ServiceRequestDownload/ServiceRequestDownload.py
vectordeprecios/core/Service/ServiceRequest/ServiceRequestDownload/__init__.py
vectordeprecios/core/main/__init__.py
vectordeprecios/core/main/vectordeprecios.py
vectordeprecios/util/Arguments.py
vectordeprecios/util/Dates.py
vectordeprecios/util/Downloader.py
vectordeprecios/util/Enumerations.py
vectordeprecios/util/Format.py
vectordeprecios/util/Installer.py
vectordeprecios/util/Output.py
vectordeprecios/util/ResponseParser.py
vectordeprecios/util/Variant.py
vectordeprecios/util/__init__.py
vectordeprecios-0.0.1.4.dist-info/LICENSE
vectordeprecios-0.0.1.4.dist-info/METADATA
vectordeprecios-0.0.1.4.dist-info/WHEEL
vectordeprecios-0.0.1.4.dist-info/top_level.txt
vectordeprecios-0.0.1.4.dist-info/RECORD
