Metadata-Version: 2.1
Name: vectordeprecios
Version: 0.0.1.4
Summary: This repository holds the vectordeprecios user Python package (client source code).
Home-page: https://github.com/BurrusFinancialIntelligence/Vector-Client.git
Author: vectordeprecios
Author-email: araveau@cclv.cl
Project-URL: Bug Tracker, https://github.com/BurrusFinancialIntelligence/Vector-Client.git/issues
Classifier: Programming Language :: Python :: 3
Classifier: License :: Other/Proprietary License
Classifier: Operating System :: OS Independent
Requires-Python: >=3.6
License-File: LICENSE
Requires-Dist: julian
Requires-Dist: numpy
Requires-Dist: pandas
Requires-Dist: python-dateutil
Requires-Dist: pytz
Requires-Dist: requests
Requires-Dist: six
Requires-Dist: urllib3
Requires-Dist: xlrd
